kobin/__init__.py
kobin/app.py
kobin/app.pyi
kobin/requests.py
kobin/requests.pyi
kobin/responses.py
kobin/responses.pyi
kobin/routes.py
kobin/routes.pyi
kobin-0.1.10.dist-info/DESCRIPTION.rst
kobin-0.1.10.dist-info/METADATA
kobin-0.1.10.dist-info/RECORD
kobin-0.1.10.dist-info/WHEEL
kobin-0.1.10.dist-info/metadata.json
kobin-0.1.10.dist-info/top_level.txt
